{ "compressionlevel":-1,
 "height":50,
 "infinite":false,
 "layers":[
        {
         "draworder":"topdown",
         "id":12,
         "name":"numDecor",
         "objects":[
                {
                 "height":0,
                 "id":5,
                 "name":"upper",
                 "point":true,
                 "properties":[
                        {
                         "name":"value",
                         "type":"int",
                         "value":1
                        }],
                 "rotation":0,
                 "type":"",
                 "visible":true,
                 "width":0,
                 "x":523.931623931624,
                 "y":606.837606837607
                },
                {
                 "height":0,
                 "id":6,
                 "name":"lower",
                 "point":true,
                 "properties":[
                        {
                         "name":"value",
                         "type":"int",
                         "value":3
                        }],
                 "rotation":0,
                 "type":"",
                 "visible":true,
                 "width":0,
                 "x":429.059829059829,
                 "y":605.128205128205
                }],
         "opacity":1,
         "type":"objectgroup",
         "visible":true,
         "x":0,
         "y":0
        },
        {
         "data":[0, 0, 0, 0, 0, 0, 0, 0, 0, 0, 0, 0, 0, 0, 0, 0, 0, 0, 0, 0, 0, 0, 0, 0, 0, 0, 0, 0, 0, 0,
            0, 0, 0, 0, 0, 0, 0, 0, 0, 0, 0, 0, 0, 0, 0, 0, 0, 0, 0, 0, 0, 0, 0, 0, 0, 0, 0, 0, 0, 0,
            0, 0, 0, 0, 0, 0, 0, 0, 0, 0, 0, 0, 0, 0, 0, 0, 0, 0, 0, 0, 0, 0, 0, 0, 0, 0, 0, 0, 0, 0,
            0, 0, 0, 0, 0, 0, 0, 0, 0, 0, 0, 0, 0, 0, 0, 0, 0, 0, 0, 0, 0, 0, 0, 0, 0, 0, 0, 0, 0, 0,
            0, 0, 0, 0, 0, 0, 0, 0, 0, 0, 0, 0, 0, 0, 0, 0, 0, 0, 0, 0, 0, 0, 0, 0, 0, 0, 0, 0, 0, 0,
            0, 0, 0, 0, 0, 0, 0, 0, 27, 27, 27, 27, 27, 27, 27, 27, 27, 27, 27, 27, 27, 27, 0, 0, 0, 0, 0, 0, 0, 0,
            0, 0, 0, 0, 0, 0, 0, 0, 27, 0, 0, 0, 0, 0, 0, 0, 0, 0, 0, 0, 0, 27, 0, 0, 0, 0, 0, 0, 0, 0,
            0, 0, 0, 0, 0, 0, 0, 0, 27, 0, 0, 0, 0, 0, 0, 0, 0, 0, 0, 0, 0, 27, 0, 0, 0, 0, 0, 0, 0, 0,
            0, 0, 0, 0, 0, 0, 0, 0, 27, 0, 0, 0, 0, 0, 0, 0, 0, 0, 0, 0, 0, 27, 0, 0, 0, 0, 0, 0, 0, 0,
            0, 0, 0, 0, 0, 0, 0, 0, 27, 0, 0, 0, 0, 0, 0, 0, 0, 0, 0, 0, 0, 27, 0, 0, 0, 0, 0, 0, 0, 0,
            0, 0, 0, 0, 0, 0, 0, 0, 27, 0, 0, 0, 0, 0, 0, 0, 0, 0, 0, 0, 0, 27, 0, 0, 0, 0, 0, 0, 0, 0,
            0, 0, 0, 0, 0, 0, 0, 0, 27, 0, 0, 0, 0, 0, 0, 0, 0, 0, 0, 0, 0, 27, 0, 0, 0, 0, 0, 0, 0, 0,
            0, 0, 0, 0, 0, 0, 0, 0, 27, 0, 0, 0, 0, 0, 0, 0, 0, 0, 0, 0, 0, 27, 0, 0, 0, 0, 0, 0, 0, 0,
            0, 0, 0, 0, 0, 0, 0, 0, 27, 0, 0, 0, 0, 0, 0, 0, 0, 0, 0, 0, 0, 27, 0, 0, 0, 0, 0, 0, 0, 0,
            0, 0, 0, 0, 0, 0, 0, 0, 27, 0, 0, 0, 0, 0, 0, 0, 0, 0, 0, 0, 0, 27, 0, 0, 0, 0, 0, 0, 0, 0,
            0, 0, 0, 0, 0, 0, 0, 0, 27, 27, 0, 0, 0, 0, 0, 0, 0, 0, 0, 0, 0, 27, 0, 0, 0, 0, 0, 0, 0, 0,
            0, 0, 0, 0, 0, 0, 0, 0, 0, 27, 0, 0, 0, 0, 0, 0, 0, 0, 0, 0, 0, 27, 0, 0, 0, 0, 0, 0, 0, 0,
            0, 0, 0, 0, 0, 0, 0, 0, 0, 27, 0, 0, 0, 0, 0, 0, 0, 0, 0, 0, 27, 27, 0, 0, 0, 0, 0, 0, 0, 0,
            0, 0, 0, 0, 0, 0, 0, 0, 0, 27, 0, 0, 0, 0, 0, 0, 0, 0, 0, 0, 27, 0, 0, 0, 0, 0, 0, 0, 0, 0,
            0, 0, 0, 0, 0, 0, 0, 0, 0, 27, 0, 0, 0, 0, 0, 0, 0, 0, 0, 0, 27, 0, 0, 0, 0, 0, 0, 0, 0, 0,
            0, 0, 0, 0, 0, 0, 0, 0, 0, 27, 0, 0, 0, 0, 0, 0, 0, 0, 0, 0, 27, 0, 0, 0, 0, 0, 0, 0, 0, 0,
            0, 0, 0, 0, 0, 0, 0, 0, 0, 27, 0, 0, 0, 0, 0, 0, 0, 0, 0, 0, 27, 0, 0, 0, 0, 0, 0, 0, 0, 0,
            0, 0, 0, 0, 0, 0, 0, 0, 0, 27, 0, 0, 0, 0, 0, 0, 0, 0, 0, 0, 27, 0, 0, 0, 0, 0, 0, 0, 0, 0,
            0, 0, 0, 0, 0, 0, 0, 0, 0, 27, 0, 0, 0, 0, 0, 0, 0, 0, 0, 0, 27, 0, 0, 0, 0, 0, 0, 0, 0, 0,
            0, 0, 0, 0, 0, 0, 0, 0, 0, 27, 0, 0, 0, 0, 0, 0, 0, 0, 0, 0, 27, 0, 0, 0, 0, 0, 0, 0, 0, 0,
            0, 0, 0, 0, 0, 0, 0, 0, 0, 27, 0, 0, 0, 0, 0, 0, 0, 0, 0, 0, 27, 0, 0, 0, 0, 0, 0, 0, 0, 0,
            0, 0, 0, 0, 0, 0, 0, 0, 0, 27, 0, 0, 0, 0, 0, 0, 0, 0, 0, 0, 27, 0, 0, 0, 0, 0, 0, 0, 0, 0,
            0, 0, 0, 0, 0, 0, 0, 0, 0, 27, 0, 0, 0, 0, 0, 0, 0, 0, 0, 0, 27, 0, 0, 0, 0, 0, 0, 0, 0, 0,
            0, 0, 0, 0, 0, 0, 0, 0, 0, 27, 0, 0, 0, 0, 0, 0, 0, 0, 0, 0, 27, 0, 0, 0, 0, 0, 0, 0, 0, 0,
            0, 0, 0, 0, 0, 0, 0, 0, 0, 27, 0, 0, 0, 0, 0, 0, 0, 0, 0, 0, 27, 0, 0, 0, 0, 0, 0, 0, 0, 0,
            0, 0, 0, 0, 0, 0, 0, 0, 0, 27, 0, 0, 0, 0, 0, 0, 0, 0, 0, 0, 27, 0, 0, 0, 0, 0, 0, 0, 0, 0,
            0, 0, 0, 0, 0, 0, 0, 0, 0, 27, 0, 0, 0, 0, 0, 0, 0, 0, 0, 0, 27, 27, 0, 0, 0, 0, 0, 0, 0, 0,
            0, 0, 0, 0, 0, 0, 0, 0, 27, 27, 0, 0, 0, 0, 0, 0, 0, 0, 0, 0, 0, 27, 0, 0, 0, 0, 0, 0, 0, 0,
            0, 0, 0, 0, 0, 0, 0, 0, 27, 0, 0, 0, 0, 0, 0, 0, 0, 0, 0, 0, 0, 27, 0, 0, 0, 0, 0, 0, 0, 0,
            0, 0, 0, 0, 0, 0, 0, 0, 27, 0, 0, 0, 0, 0, 0, 0, 0, 0, 0, 0, 0, 27, 0, 0, 0, 0, 0, 0, 0, 0,
            0, 0, 0, 0, 0, 0, 0, 0, 27, 27, 0, 0, 0, 0, 0, 0, 0, 0, 0, 0, 27, 27, 0, 0, 0, 0, 0, 0, 0, 0,
            0, 0, 0, 0, 0, 0, 0, 0, 27, 27, 0, 0, 0, 0, 0, 0, 0, 0, 0, 0, 27, 27, 0, 0, 0, 0, 0, 0, 0, 0,
            0, 0, 0, 0, 0, 0, 0, 0, 27, 0, 0, 0, 0, 0, 0, 0, 0, 0, 0, 0, 0, 27, 0, 0, 0, 0, 0, 0, 0, 0,
            0, 0, 0, 0, 0, 0, 0, 0, 27, 0, 0, 0, 0, 0, 0, 0, 0, 0, 0, 0, 0, 27, 0, 0, 0, 0, 0, 0, 0, 0,
            0, 0, 0, 0, 0, 0, 0, 0, 27, 0, 0, 0, 0, 0, 0, 0, 0, 0, 0, 0, 0, 27, 0, 0, 0, 0, 0, 0, 0, 0,
            0, 0, 0, 0, 0, 0, 0, 0, 27, 0, 0, 0, 0, 0, 0, 0, 0, 0, 0, 0, 0, 27, 0, 0, 0, 0, 0, 0, 0, 0,
            0, 0, 0, 0, 0, 0, 0, 0, 27, 0, 0, 0, 0, 0, 0, 0, 0, 0, 0, 0, 0, 27, 0, 0, 0, 0, 0, 0, 0, 0,
            0, 0, 0, 0, 0, 0, 0, 0, 27, 0, 0, 0, 0, 0, 0, 0, 0, 0, 0, 0, 0, 27, 0, 0, 0, 0, 0, 0, 0, 0,
            0, 0, 0, 0, 0, 0, 0, 0, 27, 27, 27, 27, 27, 27, 27, 27, 27, 0, 0, 27, 27, 27, 0, 0, 0, 0, 0, 0, 0, 0,
            0, 0, 0, 0, 0, 0, 0, 0, 0, 0, 0, 0, 0, 0, 0, 0, 27, 0, 0, 27, 0, 0, 0, 0, 0, 0, 0, 0, 0, 0,
            0, 0, 0, 0, 0, 0, 0, 0, 0, 0, 0, 0, 0, 0, 0, 0, 27, 0, 0, 27, 0, 0, 0, 0, 0, 0, 0, 0, 0, 0,
            0, 0, 0, 0, 0, 0, 0, 0, 0, 0, 0, 0, 0, 0, 0, 0, 27, 0, 0, 27, 0, 0, 0, 0, 0, 0, 0, 0, 0, 0,
            0, 0, 0, 0, 0, 0, 0, 0, 0, 0, 0, 0, 0, 0, 0, 0, 27, 0, 0, 27, 0, 0, 0, 0, 0, 0, 0, 0, 0, 0,
            0, 0, 0, 0, 0, 0, 0, 0, 0, 0, 0, 0, 0, 0, 0, 0, 27, 27, 27, 27, 0, 0, 0, 0, 0, 0, 0, 0, 0, 0,
            0, 0, 0, 0, 0, 0, 0, 0, 0, 0, 0, 0, 0, 0, 0, 0, 0, 0, 0, 0, 0, 0, 0, 0, 0, 0, 0, 0, 0, 0],
         "height":50,
         "id":6,
         "name":"Boundaries",
         "opacity":1,
         "type":"tilelayer",
         "visible":false,
         "width":30,
         "x":0,
         "y":0
        },
        {
         "data":[0, 0, 0, 0, 0, 0, 0, 0, 0, 0, 0, 0, 0, 0, 0, 0, 0, 0, 0, 0, 0, 0, 0, 0, 0, 0, 0, 0, 0, 0,
            0, 0, 0, 0, 0, 0, 0, 0, 0, 0, 0, 0, 0, 0, 0, 0, 0, 0, 0, 0, 0, 0, 0, 0, 0, 0, 0, 0, 0, 0,
            0, 0, 0, 0, 0, 0, 0, 0, 0, 0, 0, 0, 0, 0, 0, 0, 0, 0, 0, 0, 0, 0, 0, 0, 0, 0, 0, 0, 0, 0,
            0, 0, 0, 0, 0, 0, 0, 0, 0, 0, 0, 0, 0, 0, 0, 0, 0, 0, 0, 0, 0, 0, 0, 0, 0, 0, 0, 0, 0, 0,
            0, 0, 0, 0, 0, 0, 0, 0, 0, 0, 0, 0, 0, 0, 0, 0, 0, 0, 0, 0, 0, 0, 0, 0, 0, 0, 0, 0, 0, 0,
            0, 0, 0, 0, 0, 0, 0, 0, 0, 0, 0, 0, 0, 0, 0, 0, 0, 0, 0, 0, 0, 0, 0, 0, 0, 0, 0, 0, 0, 0,
            0, 0, 0, 0, 0, 0, 0, 0, 0, 0, 0, 0, 0, 0, 0, 0, 0, 0, 0, 0, 0, 0, 0, 0, 0, 0, 0, 0, 0, 0,
            0, 0, 0, 0, 0, 0, 0, 0, 0, 6, 6, 6, 6, 6, 6, 6, 6, 6, 6, 6, 6, 0, 0, 0, 0, 0, 0, 0, 0, 0,
            0, 0, 0, 0, 0, 0, 0, 0, 0, 6, 1, 2, 3, 3, 3, 3, 3, 3, 4, 5, 6, 0, 0, 0, 0, 0, 0, 0, 0, 0,
            0, 0, 0, 0, 0, 0, 0, 0, 0, 6, 8, 9, 10, 10, 10, 10, 10, 10, 11, 12, 6, 0, 0, 0, 0, 0, 0, 0, 0, 0,
            0, 0, 0, 0, 0, 0, 0, 0, 0, 6, 15, 16, 7, 7, 7, 7, 7, 7, 18, 19, 6, 0, 0, 0, 0, 0, 0, 0, 0, 0,
            0, 0, 0, 0, 0, 0, 0, 0, 0, 6, 15, 16, 7, 7, 7, 7, 7, 7, 18, 19, 6, 0, 0, 0, 0, 0, 0, 0, 0, 0,
            0, 0, 0, 0, 0, 0, 0, 0, 0, 6, 15, 16, 7, 7, 7, 7, 7, 7, 18, 19, 6, 0, 0, 0, 0, 0, 0, 0, 0, 0,
            0, 0, 0, 0, 0, 0, 0, 0, 0, 6, 15, 16, 7, 7, 7, 7, 7, 7, 18, 19, 6, 0, 0, 0, 0, 0, 0, 0, 0, 0,
            0, 0, 0, 0, 0, 0, 0, 0, 0, 6, 22, 23, 24, 24, 14, 13, 24, 24, 25, 26, 6, 0, 0, 0, 0, 0, 0, 0, 0, 0,
            0, 0, 0, 0, 0, 0, 0, 0, 0, 6, 29, 30, 31, 34, 16, 18, 35, 31, 32, 33, 6, 0, 0, 0, 0, 0, 0, 0, 0, 0,
            0, 0, 0, 0, 0, 0, 0, 0, 0, 6, 6, 6, 6, 15, 16, 18, 19, 6, 6, 6, 6, 0, 0, 0, 0, 0, 0, 0, 0, 0,
            0, 0, 0, 0, 0, 0, 0, 0, 0, 6, 6, 6, 6, 15, 16, 18, 19, 6, 6, 6, 6, 0, 0, 0, 0, 0, 0, 0, 0, 0,
            0, 0, 0, 0, 0, 0, 0, 0, 0, 6, 6, 6, 6, 15, 16, 18, 19, 6, 6, 6, 6, 0, 0, 0, 0, 0, 0, 0, 0, 0,
            0, 0, 0, 0, 0, 0, 0, 0, 0, 6, 6, 6, 6, 15, 16, 18, 19, 6, 6, 6, 6, 0, 0, 0, 0, 0, 0, 0, 0, 0,
            0, 0, 0, 0, 0, 0, 0, 0, 0, 6, 6, 6, 6, 15, 16, 18, 19, 6, 6, 6, 6, 0, 0, 0, 0, 0, 0, 0, 0, 0,
            0, 0, 0, 0, 0, 0, 0, 0, 0, 6, 6, 6, 6, 15, 16, 18, 19, 6, 6, 6, 0, 0, 0, 0, 0, 0, 0, 0, 0, 0,
            0, 0, 0, 0, 0, 0, 0, 0, 0, 0, 6, 6, 6, 15, 16, 18, 19, 6, 6, 6, 0, 0, 0, 0, 0, 0, 0, 0, 0, 0,
            0, 0, 0, 0, 0, 0, 0, 0, 0, 0, 6, 6, 6, 15, 16, 18, 19, 6, 6, 6, 0, 0, 0, 0, 0, 0, 0, 0, 0, 0,
            0, 0, 0, 0, 0, 0, 0, 0, 0, 0, 6, 6, 6, 15, 16, 18, 19, 6, 6, 6, 6, 0, 0, 0, 0, 0, 0, 0, 0, 0,
            0, 0, 0, 0, 0, 0, 0, 0, 0, 0, 6, 6, 6, 15, 16, 18, 19, 6, 6, 6, 6, 0, 0, 0, 0, 0, 0, 0, 0, 0,
            0, 0, 0, 0, 0, 0, 0, 0, 0, 6, 6, 6, 6, 15, 16, 18, 19, 6, 6, 6, 6, 0, 0, 0, 0, 0, 0, 0, 0, 0,
            0, 0, 0, 0, 0, 0, 0, 0, 0, 6, 6, 6, 6, 15, 16, 18, 19, 6, 6, 6, 6, 0, 0, 0, 0, 0, 0, 0, 0, 0,
            0, 0, 0, 0, 0, 0, 0, 0, 0, 6, 6, 6, 6, 15, 16, 18, 19, 6, 6, 6, 6, 0, 0, 0, 0, 0, 0, 0, 0, 0,
            0, 0, 0, 0, 0, 0, 0, 0, 0, 6, 6, 6, 6, 15, 16, 18, 19, 6, 6, 6, 6, 0, 0, 0, 0, 0, 0, 0, 0, 0,
            0, 0, 0, 0, 0, 0, 0, 0, 0, 6, 6, 6, 6, 15, 16, 18, 19, 6, 6, 6, 6, 0, 0, 0, 0, 0, 0, 0, 0, 0,
            0, 0, 0, 0, 0, 0, 0, 0, 0, 6, 6, 6, 6, 15, 16, 18, 19, 6, 6, 6, 6, 0, 0, 0, 0, 0, 0, 0, 0, 0,
            0, 0, 0, 0, 0, 0, 0, 0, 0, 6, 6, 6, 6, 15, 16, 18, 19, 6, 6, 6, 6, 0, 0, 0, 0, 0, 0, 0, 0, 0,
            0, 0, 0, 0, 0, 0, 0, 0, 0, 6, 6, 6, 6, 15, 16, 18, 19, 6, 6, 6, 6, 0, 0, 0, 0, 0, 0, 0, 0, 0,
            0, 0, 0, 0, 0, 0, 0, 0, 0, 6, 1, 2, 3, 27, 16, 18, 28, 3, 4, 5, 6, 0, 0, 0, 0, 0, 0, 0, 0, 0,
            0, 0, 0, 0, 0, 0, 0, 0, 6, 6, 8, 9, 10, 10, 21, 20, 10, 10, 11, 12, 6, 0, 0, 0, 0, 0, 0, 0, 0, 0,
            0, 0, 0, 0, 0, 0, 0, 0, 6, 6, 15, 16, 7, 7, 7, 7, 7, 7, 18, 19, 6, 6, 0, 0, 0, 0, 0, 0, 0, 0,
            0, 0, 0, 0, 0, 0, 0, 0, 6, 6, 15, 16, 7, 7, 7, 7, 7, 7, 18, 19, 6, 6, 0, 0, 0, 0, 0, 0, 0, 0,
            0, 0, 0, 0, 0, 0, 0, 0, 6, 6, 15, 16, 7, 7, 7, 7, 7, 7, 18, 19, 6, 6, 0, 0, 0, 0, 0, 0, 0, 0,
            0, 0, 0, 0, 0, 0, 0, 0, 6, 6, 15, 16, 7, 7, 7, 7, 7, 7, 18, 19, 6, 6, 0, 0, 0, 0, 0, 0, 0, 0,
            0, 0, 0, 0, 0, 0, 0, 0, 6, 6, 22, 23, 24, 24, 24, 24, 24, 24, 25, 26, 6, 6, 0, 0, 0, 0, 0, 0, 0, 0,
            0, 0, 0, 0, 0, 0, 0, 0, 6, 6, 29, 30, 31, 31, 31, 31, 31, 31, 32, 33, 6, 0, 0, 0, 0, 0, 0, 0, 0, 0,
            0, 0, 0, 0, 0, 0, 0, 0, 6, 6, 6, 6, 6, 6, 6, 6, 6, 6, 6, 6, 6, 0, 0, 0, 0, 0, 0, 0, 0, 0,
            0, 0, 0, 0, 0, 0, 0, 0, 6, 6, 6, 6, 6, 6, 6, 6, 6, 6, 6, 6, 6, 0, 0, 0, 0, 0, 0, 0, 0, 0,
            0, 0, 0, 0, 0, 0, 0, 0, 6, 0, 0, 0, 0, 0, 0, 0, 0, 6, 6, 6, 0, 0, 0, 0, 0, 0, 0, 0, 0, 0,
            0, 0, 0, 0, 0, 0, 0, 0, 6, 0, 0, 0, 0, 0, 0, 0, 0, 6, 6, 6, 0, 0, 0, 0, 0, 0, 0, 0, 0, 0,
            0, 0, 0, 0, 0, 0, 0, 0, 6, 0, 0, 0, 0, 0, 0, 0, 0, 6, 6, 6, 0, 0, 0, 0, 0, 0, 0, 0, 0, 0,
            0, 0, 0, 0, 0, 0, 0, 0, 6, 0, 0, 0, 0, 0, 0, 0, 0, 6, 6, 6, 0, 0, 0, 0, 0, 0, 0, 0, 0, 0,
            0, 0, 0, 0, 0, 0, 0, 0, 6, 0, 0, 0, 0, 0, 0, 0, 0, 6, 6, 6, 0, 0, 0, 0, 0, 0, 0, 0, 0, 0,
            0, 0, 0, 0, 0, 0, 0, 0, 0, 0, 0, 0, 0, 0, 0, 0, 0, 6, 6, 6, 0, 0, 0, 0, 0, 0, 0, 0, 0, 0],
         "height":50,
         "id":1,
         "name":"DrawTiles",
         "opacity":1,
         "type":"tilelayer",
         "visible":true,
         "width":30,
         "x":0,
         "y":0
        },
        {
         "data":[0, 0, 0, 0, 0, 0, 0, 67, 68, 69, 68, 67, 68, 69, 70, 364, 365, 365, 366, 364, 365, 366, 367, 0, 0, 0, 0, 0, 0, 0,
            0, 0, 0, 0, 0, 0, 0, 74, 75, 76, 75, 74, 75, 76, 77, 371, 372, 372, 373, 371, 372, 373, 374, 0, 0, 0, 0, 0, 0, 0,
            0, 0, 0, 0, 0, 0, 0, 81, 82, 83, 82, 81, 82, 83, 84, 378, 379, 379, 380, 378, 379, 380, 381, 0, 0, 0, 0, 0, 0, 0,
            0, 0, 0, 0, 0, 0, 0, 0, 0, 90, 89, 88, 89, 90, 91, 385, 386, 386, 387, 385, 386, 39, 40, 41, 40, 41, 42, 0, 0, 0,
            0, 0, 0, 0, 0, 0, 0, 0, 0, 97, 96, 95, 96, 97, 98, 392, 393, 393, 394, 392, 393, 46, 47, 48, 47, 48, 49, 0, 0, 0,
            0, 0, 0, 0, 0, 0, 0, 0, 0, 104, 103, 102, 103, 104, 105, 399, 400, 400, 401, 399, 400, 46, 47, 48, 47, 48, 49, 0, 0, 0,
            0, 0, 0, 0, 0, 0, 0, 0, 0, 111, 110, 109, 110, 111, 112, 406, 407, 407, 408, 406, 407, 46, 47, 48, 47, 48, 49, 0, 0, 0,
            0, 0, 0, 0, 0, 0, 0, 0, 0, 0, 0, 0, 0, 0, 0, 0, 0, 0, 0, 0, 0, 53, 54, 55, 54, 55, 56, 0, 0, 0,
            0, 0, 0, 0, 0, 0, 0, 0, 0, 0, 0, 0, 0, 0, 0, 0, 0, 0, 0, 0, 0, 60, 61, 62, 0, 0, 0, 0, 0, 0,
            0, 0, 0, 0, 0, 0, 0, 0, 0, 0, 0, 0, 0, 0, 0, 0, 0, 0, 0, 0, 0, 67, 68, 69, 0, 0, 0, 0, 0, 0,
            0, 0, 0, 0, 0, 0, 0, 0, 0, 0, 0, 0, 0, 0, 0, 0, 0, 0, 0, 0, 0, 74, 75, 76, 0, 0, 0, 0, 0, 0,
            0, 0, 0, 0, 0, 0, 0, 0, 0, 0, 0, 0, 0, 0, 0, 0, 0, 0, 0, 0, 0, 81, 82, 83, 0, 0, 0, 0, 0, 0,
            0, 410, 411, 412, 413, 414, 415, 414, 415, 416, 0, 0, 0, 0, 0, 0, 0, 0, 0, 0, 0, 88, 89, 90, 0, 0, 0, 0, 0, 0,
            0, 429, 430, 431, 432, 433, 434, 433, 434, 435, 0, 0, 0, 0, 0, 0, 0, 0, 0, 0, 627, 0, 0, 0, 0, 0, 0, 0, 0, 0,
            0, 429, 430, 431, 432, 433, 432, 433, 434, 435, 0, 0, 0, 0, 0, 0, 0, 0, 0, 0, 633, 0, 0, 0, 0, 0, 0, 0, 0, 0,
            0, 448, 449, 450, 451, 452, 451, 452, 453, 454, 638, 639, 0, 0, 0, 0, 0, 0, 640, 641, 639, 0, 0, 0, 0, 0, 0, 0, 0, 0,
            0, 467, 468, 469, 470, 471, 470, 471, 472, 473, 644, 645, 0, 0, 0, 0, 0, 0, 646, 647, 645, 0, 0, 0, 0, 0, 0, 0, 0, 0,
            0, 486, 487, 488, 489, 490, 489, 490, 491, 492, 0, 0, 0, 0, 0, 0, 0, 0, 0, 0, 0, 0, 0, 0, 0, 0, 0, 0, 0, 0,
            0, 505, 506, 507, 508, 509, 508, 509, 510, 511, 0, 0, 0, 0, 0, 0, 0, 0, 0, 0, 0, 0, 0, 0, 0, 0, 0, 0, 0, 0,
            0, 524, 525, 526, 527, 528, 527, 528, 529, 530, 0, 0, 0, 0, 0, 0, 0, 0, 0, 0, 0, 0, 0, 0, 0, 0, 0, 0, 0, 0,
            0, 562, 563, 545, 546, 547, 546, 547, 548, 549, 0, 0, 0, 0, 0, 0, 0, 0, 0, 0, 0, 0, 0, 0, 0, 0, 0, 0, 0, 0,
            0, 581, 582, 564, 565, 566, 565, 566, 567, 568, 0, 0, 0, 0, 0, 0, 0, 0, 0, 0, 113, 114, 115, 116, 117, 115, 116, 117, 118, 119,
            0, 600, 601, 0, 0, 0, 0, 0, 0, 0, 0, 0, 0, 0, 0, 0, 0, 0, 0, 0, 133, 134, 135, 136, 137, 135, 136, 137, 138, 139,
            0, 0, 0, 0, 0, 0, 0, 0, 0, 0, 0, 0, 0, 0, 0, 0, 0, 0, 0, 0, 133, 134, 135, 136, 137, 135, 136, 137, 138, 139,
            0, 0, 0, 0, 0, 0, 0, 0, 0, 0, 0, 0, 0, 0, 0, 0, 0, 0, 0, 0, 153, 154, 155, 156, 157, 155, 156, 157, 158, 159,
            0, 0, 0, 0, 0, 0, 0, 0, 0, 0, 0, 0, 0, 0, 0, 0, 0, 0, 0, 0, 173, 174, 175, 176, 177, 175, 176, 177, 178, 179,
            0, 0, 0, 0, 0, 0, 0, 0, 0, 0, 0, 0, 0, 0, 0, 0, 0, 0, 0, 0, 193, 194, 195, 196, 197, 195, 196, 197, 198, 199,
            0, 0, 0, 0, 0, 0, 0, 0, 0, 0, 0, 0, 0, 0, 0, 0, 0, 0, 0, 0, 213, 214, 215, 216, 217, 215, 216, 217, 218, 219,
            0, 0, 0, 0, 0, 0, 0, 0, 0, 0, 0, 0, 0, 0, 0, 0, 0, 0, 0, 0, 233, 234, 235, 236, 237, 235, 236, 237, 238, 239,
            0, 0, 0, 0, 0, 0, 0, 0, 0, 0, 0, 0, 0, 0, 0, 0, 0, 0, 0, 0, 253, 254, 255, 256, 257, 255, 256, 257, 258, 259,
            0, 0, 0, 0, 0, 0, 0, 0, 0, 0, 0, 0, 0, 0, 0, 0, 0, 0, 0, 0, 273, 274, 275, 276, 277, 275, 276, 277, 278, 279,
            0, 0, 0, 0, 0, 0, 0, 0, 0, 0, 0, 0, 0, 0, 0, 0, 0, 0, 0, 0, 293, 0, 0, 0, 0, 0, 0, 0, 0, 0,
            0, 0, 0, 0, 0, 0, 0, 0, 0, 279, 0, 0, 0, 0, 0, 0, 0, 0, 0, 0, 313, 0, 0, 0, 0, 0, 0, 0, 0, 0,
            0, 0, 0, 0, 0, 0, 0, 0, 0, 0, 0, 0, 0, 0, 0, 0, 0, 0, 0, 0, 0, 0, 0, 0, 0, 0, 0, 0, 0, 0,
            0, 0, 0, 0, 0, 0, 0, 0, 0, 0, 0, 0, 0, 0, 0, 0, 0, 0, 0, 0, 0, 0, 0, 0, 0, 0, 0, 0, 0, 0,
            0, 0, 0, 0, 0, 0, 0, 0, 640, 641, 642, 0, 0, 0, 0, 0, 0, 0, 0, 640, 641, 642, 0, 0, 0, 0, 0, 0, 0, 0,
            0, 0, 0, 0, 0, 0, 0, 0, 646, 647, 648, 0, 0, 0, 0, 0, 0, 0, 0, 646, 647, 648, 0, 0, 0, 0, 0, 0, 0, 0,
            0, 0, 0, 0, 0, 0, 0, 0, 0, 0, 0, 0, 0, 0, 0, 0, 0, 0, 0, 0, 0, 0, 0, 0, 0, 0, 0, 0, 0, 0,
            0, 0, 0, 0, 0, 0, 0, 0, 0, 0, 0, 0, 0, 0, 0, 0, 0, 0, 0, 0, 0, 0, 0, 0, 0, 0, 0, 0, 0, 0,
            0, 0, 0, 0, 0, 0, 0, 0, 0, 0, 0, 0, 0, 0, 0, 0, 0, 0, 0, 0, 0, 0, 0, 0, 0, 0, 0, 0, 0, 0,
            0, 0, 0, 0, 0, 0, 0, 0, 0, 39, 40, 41, 40, 41, 40, 41, 42, 0, 0, 0, 0, 0, 0, 0, 0, 0, 0, 0, 0, 0,
            0, 0, 0, 0, 0, 0, 0, 0, 0, 46, 47, 48, 47, 48, 47, 48, 49, 0, 0, 113, 114, 115, 114, 115, 116, 115, 116, 117, 118, 119,
            0, 0, 0, 0, 0, 0, 0, 0, 0, 53, 54, 55, 54, 55, 54, 55, 56, 0, 0, 133, 134, 135, 134, 135, 136, 135, 136, 137, 138, 139,
            0, 0, 0, 0, 0, 0, 0, 0, 0, 60, 61, 62, 61, 62, 61, 62, 63, 0, 0, 153, 154, 155, 156, 157, 158, 158, 158, 157, 158, 159,
            0, 0, 0, 0, 0, 0, 0, 0, 0, 67, 68, 69, 68, 69, 68, 69, 70, 0, 0, 173, 174, 175, 174, 175, 176, 175, 176, 177, 178, 179,
            0, 0, 0, 0, 0, 0, 0, 0, 0, 74, 75, 76, 75, 76, 75, 76, 77, 0, 0, 193, 194, 195, 194, 195, 196, 195, 196, 197, 198, 199,
            0, 0, 0, 0, 0, 0, 0, 0, 0, 81, 82, 83, 82, 83, 82, 83, 84, 0, 0, 213, 214, 215, 214, 215, 216, 215, 216, 217, 218, 219,
            0, 0, 0, 0, 0, 0, 0, 0, 0, 88, 89, 90, 89, 90, 89, 90, 91, 0, 0, 233, 234, 235, 234, 235, 236, 235, 236, 237, 238, 239,
            0, 0, 0, 0, 0, 0, 0, 0, 0, 95, 96, 97, 96, 97, 96, 97, 98, 0, 0, 253, 254, 255, 254, 255, 256, 255, 256, 257, 258, 259,
            0, 0, 0, 0, 0, 0, 0, 0, 0, 102, 103, 104, 103, 104, 103, 104, 105, 0, 0, 273, 274, 275, 274, 275, 276, 275, 276, 277, 278, 279],
         "height":50,
         "id":2,
         "name":"Decor1",
         "opacity":1,
         "type":"tilelayer",
         "visible":true,
         "width":30,
         "x":0,
         "y":0
        },
        {
         "data":[0, 0, 0, 0, 0, 0, 0, 0, 64, 0, 0, 0, 0, 64, 0, 0, 376, 0, 0, 0, 0, 376, 0, 0, 0, 0, 0, 0, 0, 0,
            0, 0, 0, 0, 0, 0, 0, 0, 71, 0, 0, 0, 0, 71, 0, 0, 383, 0, 0, 0, 0, 383, 0, 0, 0, 0, 0, 0, 0, 0,
            0, 0, 0, 0, 0, 0, 0, 0, 64, 0, 0, 0, 0, 64, 0, 0, 376, 0, 0, 0, 0, 376, 0, 0, 0, 0, 0, 0, 0, 0,
            0, 0, 0, 336, 337, 338, 337, 338, 339, 0, 0, 0, 0, 71, 0, 0, 383, 0, 0, 0, 0, 0, 0, 0, 0, 0, 0, 0, 0, 0,
            0, 0, 0, 343, 344, 345, 344, 345, 346, 0, 92, 93, 0, 64, 0, 0, 376, 0, 389, 390, 0, 0, 0, 0, 0, 0, 0, 0, 0, 0,
            0, 0, 0, 343, 344, 345, 344, 345, 346, 0, 99, 100, 0, 71, 0, 0, 383, 0, 396, 397, 0, 0, 0, 0, 0, 0, 0, 0, 0, 0,
            0, 0, 0, 350, 351, 352, 351, 352, 353, 0, 106, 107, 0, 0, 0, 0, 0, 0, 403, 404, 0, 0, 0, 0, 0, 0, 0, 0, 0, 0,
            0, 0, 0, 357, 358, 359, 358, 359, 360, 0, 0, 0, 0, 0, 0, 0, 0, 0, 0, 0, 0, 0, 0, 0, 0, 0, 0, 0, 0, 0,
            0, 0, 0, 364, 365, 366, 365, 366, 367, 0, 0, 0, 0, 0, 0, 0, 0, 0, 0, 0, 0, 0, 0, 0, 68, 69, 70, 0, 0, 0,
            0, 0, 0, 371, 372, 373, 372, 373, 374, 0, 0, 0, 0, 0, 0, 0, 0, 0, 0, 0, 0, 0, 0, 0, 75, 76, 77, 0, 0, 0,
            0, 0, 0, 378, 379, 380, 379, 380, 381, 0, 0, 0, 0, 0, 0, 0, 0, 0, 0, 0, 0, 0, 0, 0, 82, 83, 84, 0, 0, 0,
            0, 0, 0, 378, 379, 380, 386, 387, 388, 0, 0, 0, 0, 0, 0, 0, 0, 0, 0, 0, 0, 0, 0, 0, 89, 90, 91, 0, 0, 0,
            0, 0, 0, 0, 0, 0, 0, 0, 0, 0, 0, 0, 0, 0, 0, 0, 0, 0, 0, 0, 0, 0, 0, 0, 96, 97, 98, 0, 0, 0,
            0, 0, 0, 0, 0, 0, 0, 0, 0, 0, 0, 0, 0, 0, 0, 0, 0, 0, 0, 0, 410, 411, 412, 411, 412, 413, 414, 415, 416, 0,
            0, 0, 0, 0, 0, 0, 0, 0, 0, 0, 0, 0, 0, 0, 0, 0, 0, 0, 0, 0, 429, 430, 431, 430, 431, 432, 433, 434, 435, 0,
            0, 0, 0, 0, 0, 0, 0, 0, 0, 0, 641, 642, 0, 0, 0, 0, 0, 0, 637, 638, 448, 449, 450, 449, 450, 451, 452, 453, 454, 0,
            0, 0, 0, 0, 0, 0, 0, 0, 0, 0, 647, 648, 0, 0, 0, 0, 0, 0, 643, 644, 467, 468, 469, 468, 469, 470, 471, 472, 473, 0,
            0, 0, 503, 504, 0, 462, 0, 500, 501, 0, 0, 0, 0, 0, 0, 0, 0, 0, 0, 0, 486, 487, 488, 487, 488, 489, 490, 491, 492, 0,
            0, 0, 522, 523, 0, 481, 0, 519, 520, 0, 0, 0, 0, 0, 0, 0, 0, 0, 0, 0, 505, 506, 507, 506, 507, 508, 509, 510, 511, 0,
            0, 0, 0, 0, 0, 0, 0, 0, 0, 0, 0, 0, 0, 0, 0, 0, 0, 0, 0, 0, 524, 525, 526, 525, 526, 527, 528, 529, 530, 0,
            0, 0, 500, 501, 0, 426, 0, 503, 504, 0, 0, 0, 0, 0, 0, 0, 0, 0, 0, 0, 543, 544, 545, 544, 545, 546, 547, 548, 549, 0,
            0, 0, 519, 520, 0, 445, 0, 522, 523, 0, 0, 0, 0, 0, 0, 0, 0, 0, 0, 0, 0, 0, 0, 0, 0, 0, 0, 0, 0, 0,
            0, 0, 0, 113, 114, 115, 116, 117, 118, 119, 0, 0, 0, 0, 0, 0, 0, 0, 0, 0, 0, 0, 0, 0, 0, 0, 0, 0, 0, 0,
            0, 0, 0, 133, 134, 135, 136, 137, 138, 139, 0, 0, 0, 0, 0, 0, 0, 0, 0, 0, 0, 0, 0, 0, 0, 0, 0, 0, 0, 0,
            0, 0, 0, 133, 134, 135, 136, 137, 138, 139, 0, 0, 0, 0, 0, 0, 0, 0, 0, 0, 0, 0, 0, 0, 0, 0, 0, 0, 0, 0,
            0, 0, 0, 133, 134, 135, 136, 137, 138, 139, 0, 0, 0, 0, 0, 0, 0, 0, 0, 0, 0, 0, 0, 0, 0, 0, 0, 0, 0, 0,
            0, 0, 0, 153, 154, 155, 156, 157, 158, 159, 0, 0, 0, 0, 0, 0, 0, 0, 0, 0, 0, 228, 229, 0, 231, 232, 0, 228, 229, 0,
            0, 0, 0, 173, 174, 175, 176, 177, 178, 179, 0, 0, 0, 0, 0, 0, 0, 0, 0, 0, 0, 248, 249, 0, 251, 252, 0, 248, 249, 0,
            0, 0, 0, 193, 194, 195, 196, 197, 198, 199, 0, 0, 0, 0, 0, 0, 0, 0, 0, 0, 0, 0, 0, 0, 0, 0, 0, 0, 0, 0,
            0, 0, 0, 213, 214, 215, 216, 217, 218, 219, 0, 0, 0, 0, 0, 0, 0, 0, 0, 0, 0, 231, 232, 0, 228, 229, 0, 228, 229, 0,
            0, 0, 0, 233, 234, 235, 236, 237, 238, 239, 0, 0, 0, 0, 0, 0, 0, 0, 0, 0, 0, 251, 252, 0, 248, 249, 0, 248, 249, 0,
            0, 0, 0, 253, 254, 255, 256, 257, 258, 259, 0, 0, 0, 0, 0, 0, 0, 0, 0, 0, 0, 410, 411, 412, 413, 414, 413, 414, 415, 416,
            410, 411, 412, 413, 414, 415, 414, 415, 416, 0, 0, 0, 0, 0, 0, 0, 0, 0, 0, 0, 0, 429, 430, 431, 432, 431, 432, 433, 434, 435,
            429, 430, 431, 432, 433, 434, 433, 434, 435, 0, 0, 0, 0, 0, 0, 0, 0, 0, 0, 0, 0, 429, 430, 431, 432, 431, 432, 433, 434, 435,
            429, 430, 431, 432, 433, 432, 433, 434, 435, 0, 0, 0, 0, 0, 0, 0, 0, 0, 0, 0, 0, 429, 430, 431, 432, 431, 432, 433, 434, 435,
            448, 449, 450, 451, 452, 453, 452, 453, 454, 638, 639, 0, 0, 0, 0, 0, 0, 0, 0, 637, 638, 429, 430, 431, 432, 431, 432, 433, 434, 435,
            467, 468, 469, 470, 471, 470, 471, 472, 473, 644, 645, 0, 0, 0, 0, 0, 0, 0, 0, 643, 644, 448, 449, 450, 451, 452, 453, 452, 453, 454,
            486, 487, 488, 489, 490, 491, 490, 491, 492, 0, 0, 0, 0, 0, 0, 0, 0, 0, 0, 0, 0, 467, 468, 468, 469, 470, 471, 470, 471, 473,
            505, 506, 507, 508, 509, 510, 509, 510, 511, 0, 0, 0, 0, 0, 0, 0, 0, 0, 0, 0, 0, 486, 487, 487, 488, 489, 490, 489, 490, 492,
            524, 525, 526, 527, 528, 529, 528, 529, 530, 0, 0, 0, 0, 0, 0, 0, 0, 0, 0, 0, 0, 505, 506, 506, 507, 508, 509, 508, 509, 511,
            543, 544, 545, 546, 547, 548, 547, 548, 549, 0, 0, 0, 0, 0, 0, 0, 0, 0, 0, 0, 0, 524, 525, 525, 526, 527, 528, 527, 528, 530,
            562, 563, 564, 565, 566, 567, 566, 567, 568, 0, 0, 0, 0, 0, 0, 0, 0, 0, 0, 0, 0, 0, 0, 0, 0, 0, 0, 0, 0, 0,
            467, 468, 469, 470, 488, 489, 490, 491, 492, 0, 0, 0, 0, 0, 0, 0, 0, 0, 0, 0, 0, 0, 0, 0, 0, 0, 0, 0, 0, 0,
            486, 487, 488, 489, 507, 508, 509, 510, 511, 0, 0, 0, 0, 0, 0, 0, 0, 0, 0, 0, 0, 0, 0, 0, 0, 0, 0, 0, 0, 0,
            505, 506, 507, 508, 526, 527, 528, 529, 530, 0, 0, 64, 0, 0, 64, 0, 0, 0, 0, 0, 0, 0, 0, 0, 0, 0, 0, 0, 0, 0,
            524, 525, 526, 527, 545, 546, 547, 548, 549, 0, 0, 71, 0, 0, 71, 0, 0, 0, 0, 0, 0, 0, 0, 0, 0, 0, 0, 0, 0, 0,
            543, 544, 545, 546, 564, 565, 566, 567, 568, 0, 0, 64, 0, 0, 64, 0, 0, 0, 0, 0, 0, 0, 0, 0, 0, 0, 0, 0, 0, 0,
            562, 563, 564, 565, 583, 584, 585, 586, 587, 0, 0, 71, 0, 0, 71, 0, 0, 0, 0, 0, 0, 0, 0, 0, 0, 0, 0, 0, 0, 0,
            600, 601, 602, 603, 602, 603, 604, 605, 606, 0, 0, 64, 0, 0, 64, 0, 0, 0, 0, 0, 0, 0, 0, 0, 0, 0, 0, 0, 0, 0,
            0, 0, 0, 0, 0, 0, 0, 0, 0, 0, 0, 71, 0, 0, 71, 0, 0, 0, 0, 0, 0, 0, 0, 0, 0, 0, 0, 0, 0, 0],
         "height":50,
         "id":3,
         "name":"Decor2",
         "opacity":1,
         "type":"tilelayer",
         "visible":true,
         "width":30,
         "x":0,
         "y":0
        },
        {
         "data":[0, 0, 0, 0, 0, 0, 0, 0, 0, 0, 0, 0, 0, 0, 0, 0, 0, 0, 0, 0, 0, 0, 0, 0, 0, 0, 0, 0, 0, 0,
            0, 0, 0, 0, 0, 0, 0, 0, 0, 0, 0, 0, 0, 0, 0, 0, 0, 0, 0, 0, 0, 0, 0, 0, 0, 0, 0, 0, 0, 0,
            0, 0, 0, 0, 0, 0, 0, 0, 0, 0, 0, 0, 0, 0, 0, 0, 0, 0, 0, 0, 0, 0, 0, 0, 0, 0, 0, 0, 0, 0,
            0, 0, 0, 0, 0, 0, 0, 0, 0, 0, 0, 0, 0, 0, 0, 0, 0, 0, 0, 0, 0, 0, 0, 0, 0, 0, 0, 0, 0, 0,
            0, 0, 0, 0, 0, 0, 0, 0, 0, 0, 0, 0, 0, 0, 0, 0, 0, 0, 0, 0, 0, 0, 0, 0, 0, 0, 0, 0, 0, 0,
            0, 0, 0, 0, 0, 0, 0, 0, 0, 0, 0, 0, 0, 0, 0, 0, 0, 0, 0, 0, 0, 0, 0, 0, 0, 0, 0, 0, 0, 0,
            0, 0, 0, 0, 0, 0, 0, 0, 0, 0, 0, 0, 0, 0, 0, 0, 0, 0, 0, 0, 0, 0, 0, 0, 0, 0, 0, 0, 0, 0,
            0, 0, 0, 0, 0, 0, 0, 0, 0, 0, 0, 0, 0, 0, 0, 0, 0, 0, 0, 0, 0, 0, 0, 0, 0, 0, 0, 0, 0, 0,
            0, 0, 0, 0, 376, 0, 0, 376, 0, 0, 0, 0, 0, 0, 0, 0, 0, 0, 0, 0, 0, 0, 0, 0, 0, 0, 0, 0, 0, 0,
            0, 0, 0, 0, 383, 0, 0, 383, 0, 0, 0, 0, 0, 0, 0, 0, 0, 0, 0, 0, 0, 0, 0, 0, 0, 0, 0, 0, 0, 0,
            0, 0, 0, 0, 376, 0, 0, 376, 0, 0, 0, 0, 0, 0, 0, 0, 0, 0, 0, 0, 0, 0, 0, 0, 0, 0, 0, 0, 0, 0,
            0, 0, 0, 0, 383, 0, 0, 383, 0, 0, 0, 0, 0, 0, 0, 0, 0, 0, 0, 0, 0, 0, 0, 0, 0, 0, 0, 0, 0, 0,
            0, 0, 0, 0, 0, 0, 0, 0, 0, 0, 0, 0, 0, 0, 0, 0, 0, 0, 0, 0, 0, 0, 0, 0, 0, 0, 0, 0, 0, 0,
            0, 0, 0, 0, 0, 0, 0, 0, 0, 0, 0, 0, 0, 0, 0, 0, 0, 0, 0, 0, 0, 0, 0, 0, 0, 0, 0, 0, 0, 0,
            0, 0, 0, 0, 0, 0, 0, 0, 0, 0, 0, 0, 0, 0, 0, 0, 0, 0, 0, 0, 0, 0, 0, 0, 0, 0, 0, 0, 0, 0,
            0, 0, 0, 0, 0, 0, 0, 0, 0, 0, 0, 0, 0, 0, 0, 0, 0, 0, 0, 0, 0, 0, 449, 450, 451, 451, 452, 453, 454, 0,
            0, 0, 0, 0, 0, 0, 0, 0, 0, 0, 0, 0, 0, 0, 0, 0, 0, 0, 0, 0, 0, 0, 0, 0, 0, 0, 0, 0, 0, 0,
            0, 0, 0, 0, 0, 0, 0, 0, 0, 0, 0, 0, 0, 0, 0, 0, 0, 0, 0, 0, 0, 424, 0, 0, 462, 0, 0, 0, 0, 0,
            0, 0, 0, 0, 0, 0, 0, 0, 0, 0, 0, 0, 0, 0, 0, 0, 0, 0, 0, 0, 0, 443, 0, 0, 481, 0, 577, 578, 0, 0,
            0, 0, 0, 0, 0, 0, 0, 0, 0, 0, 0, 0, 0, 0, 0, 0, 0, 0, 0, 0, 0, 426, 0, 0, 464, 0, 596, 597, 0, 0,
            0, 0, 0, 0, 0, 0, 0, 0, 0, 0, 0, 0, 0, 0, 0, 0, 0, 0, 0, 0, 0, 445, 0, 0, 483, 0, 615, 616, 0, 0,
            0, 0, 0, 0, 0, 0, 0, 0, 0, 0, 0, 0, 0, 0, 0, 0, 0, 0, 0, 0, 0, 0, 0, 0, 0, 0, 0, 0, 0, 0,
            0, 0, 0, 0, 0, 0, 0, 0, 0, 0, 0, 0, 0, 0, 0, 0, 0, 0, 0, 0, 0, 0, 0, 0, 0, 0, 0, 0, 0, 0,
            0, 0, 0, 0, 0, 0, 0, 0, 0, 0, 0, 0, 0, 0, 0, 0, 0, 0, 0, 0, 0, 0, 0, 0, 0, 0, 0, 0, 0, 0,
            0, 0, 0, 0, 0, 0, 0, 0, 0, 0, 0, 0, 0, 0, 0, 0, 0, 0, 0, 0, 0, 0, 0, 0, 0, 0, 0, 0, 0, 0,
            0, 0, 0, 0, 0, 0, 0, 0, 0, 0, 0, 0, 0, 0, 0, 0, 0, 0, 0, 0, 0, 0, 0, 0, 0, 0, 0, 0, 0, 0,
            0, 0, 0, 0, 0, 0, 0, 0, 0, 0, 0, 0, 0, 0, 0, 0, 0, 0, 0, 0, 0, 0, 0, 0, 0, 0, 0, 0, 0, 0,
            0, 0, 0, 0, 0, 0, 0, 0, 0, 0, 0, 0, 0, 0, 0, 0, 0, 0, 0, 0, 0, 0, 0, 0, 0, 0, 0, 0, 0, 0,
            0, 0, 0, 0, 150, 0, 148, 0, 152, 0, 0, 0, 0, 0, 0, 0, 0, 0, 0, 0, 0, 0, 0, 0, 0, 0, 0, 0, 0, 0,
            0, 0, 0, 0, 170, 0, 168, 0, 172, 0, 0, 0, 0, 0, 0, 0, 0, 0, 0, 0, 0, 0, 0, 0, 0, 0, 0, 0, 0, 0,
            0, 0, 0, 0, 152, 0, 188, 0, 150, 0, 0, 0, 0, 0, 0, 0, 0, 0, 0, 0, 0, 0, 0, 0, 0, 0, 0, 0, 0, 0,
            0, 0, 0, 0, 172, 0, 208, 0, 170, 0, 0, 0, 0, 0, 0, 0, 0, 0, 0, 0, 0, 0, 0, 0, 0, 0, 0, 0, 0, 0,
            0, 0, 0, 0, 0, 0, 0, 0, 0, 0, 0, 0, 0, 0, 0, 0, 0, 0, 0, 0, 0, 0, 0, 0, 0, 0, 0, 0, 0, 0,
            0, 0, 0, 0, 0, 0, 0, 0, 0, 0, 0, 0, 0, 0, 0, 0, 0, 0, 0, 0, 0, 0, 0, 0, 0, 0, 0, 0, 0, 0,
            0, 0, 0, 0, 0, 0, 0, 0, 0, 0, 0, 0, 0, 0, 0, 0, 0, 0, 0, 0, 0, 0, 0, 0, 0, 0, 0, 0, 0, 0,
            0, 0, 0, 0, 0, 0, 0, 0, 0, 0, 0, 0, 0, 0, 0, 0, 0, 0, 0, 0, 0, 0, 0, 0, 0, 0, 0, 0, 0, 0,
            0, 426, 0, 500, 501, 0, 500, 504, 0, 0, 0, 0, 0, 0, 0, 0, 0, 0, 0, 0, 0, 0, 0, 0, 0, 0, 0, 0, 0, 0,
            0, 445, 0, 519, 520, 0, 519, 523, 0, 0, 0, 0, 0, 0, 0, 0, 0, 0, 0, 0, 0, 0, 0, 0, 0, 0, 0, 0, 0, 0,
            0, 0, 0, 0, 0, 0, 0, 0, 0, 0, 0, 0, 0, 0, 0, 0, 0, 0, 0, 0, 0, 0, 500, 501, 0, 424, 0, 503, 504, 0,
            0, 464, 0, 503, 504, 0, 503, 501, 0, 0, 0, 0, 0, 0, 0, 0, 0, 0, 0, 0, 0, 0, 519, 520, 0, 443, 0, 522, 523, 0,
            0, 483, 0, 522, 523, 0, 522, 520, 0, 0, 0, 0, 0, 0, 0, 0, 0, 0, 0, 0, 0, 0, 503, 504, 0, 426, 0, 500, 501, 0,
            0, 0, 0, 0, 0, 0, 0, 0, 0, 0, 0, 0, 0, 0, 0, 0, 0, 0, 0, 0, 0, 0, 0, 0, 0, 0, 0, 0, 0, 0,
            0, 424, 0, 500, 501, 0, 500, 501, 0, 0, 0, 0, 0, 0, 0, 0, 0, 0, 0, 0, 0, 0, 0, 0, 0, 0, 0, 0, 0, 0,
            0, 443, 0, 519, 520, 0, 519, 520, 0, 0, 0, 0, 0, 0, 0, 0, 0, 0, 0, 0, 0, 0, 0, 0, 0, 0, 0, 0, 0, 0,
            0, 0, 0, 0, 0, 0, 0, 0, 0, 0, 0, 0, 0, 0, 0, 0, 0, 0, 0, 0, 0, 0, 0, 0, 0, 0, 0, 0, 0, 0,
            0, 464, 0, 503, 504, 0, 503, 504, 0, 0, 0, 0, 0, 0, 0, 0, 0, 0, 0, 0, 0, 0, 0, 0, 0, 0, 0, 0, 0, 0,
            0, 483, 0, 522, 523, 0, 522, 523, 0, 0, 0, 0, 0, 0, 0, 0, 0, 0, 0, 0, 0, 0, 0, 0, 0, 0, 0, 0, 0, 0,
            0, 0, 0, 0, 0, 0, 0, 0, 0, 0, 0, 0, 0, 0, 0, 0, 0, 0, 0, 0, 0, 0, 0, 0, 0, 0, 0, 0, 0, 0,
            0, 0, 0, 0, 0, 0, 0, 0, 0, 0, 0, 0, 0, 0, 0, 0, 0, 0, 0, 0, 0, 0, 0, 0, 0, 0, 0, 0, 0, 0,
            0, 0, 0, 0, 0, 0, 0, 0, 0, 0, 0, 0, 0, 0, 0, 0, 0, 0, 0, 0, 0, 0, 0, 0, 0, 0, 0, 0, 0, 0],
         "height":50,
         "id":5,
         "name":"Decor3",
         "opacity":1,
         "type":"tilelayer",
         "visible":true,
         "width":30,
         "x":0,
         "y":0
        },
        {
         "data":[0, 0, 0, 0, 0, 0, 0, 0, 0, 0, 0, 0, 0, 0, 0, 0, 0, 0, 0, 0, 0, 0, 0, 0, 0, 0, 0, 0, 0, 0,
            0, 0, 0, 0, 0, 0, 0, 0, 0, 0, 0, 0, 0, 0, 0, 0, 0, 0, 0, 0, 0, 0, 0, 0, 0, 0, 0, 0, 0, 0,
            0, 0, 0, 0, 0, 0, 0, 0, 0, 0, 0, 0, 0, 0, 0, 0, 0, 0, 0, 0, 0, 0, 0, 0, 0, 0, 0, 0, 0, 0,
            0, 0, 0, 0, 0, 0, 0, 0, 0, 0, 0, 0, 0, 0, 0, 0, 0, 0, 0, 0, 0, 0, 0, 0, 0, 0, 0, 0, 0, 0,
            0, 0, 0, 0, 0, 0, 0, 0, 0, 0, 0, 0, 0, 0, 0, 0, 0, 0, 0, 0, 0, 0, 0, 0, 0, 0, 0, 0, 0, 0,
            0, 0, 0, 0, 0, 0, 0, 0, 0, 0, 0, 0, 0, 0, 0, 0, 0, 0, 0, 0, 0, 0, 0, 0, 0, 0, 0, 0, 0, 0,
            0, 0, 0, 0, 0, 0, 0, 0, 0, 0, 0, 0, 0, 0, 0, 0, 0, 0, 0, 0, 0, 0, 0, 0, 0, 0, 0, 0, 0, 0,
            0, 0, 0, 0, 0, 0, 0, 0, 0, 0, 0, 0, 0, 0, 0, 0, 0, 0, 0, 0, 0, 0, 0, 0, 0, 0, 0, 0, 0, 0,
            0, 0, 0, 0, 0, 0, 0, 0, 0, 0, 0, 0, 0, 0, 0, 0, 0, 0, 0, 0, 0, 0, 0, 0, 0, 0, 0, 0, 0, 0,
            0, 0, 0, 0, 0, 0, 0, 0, 0, 0, 0, 0, 0, 0, 0, 0, 0, 0, 0, 0, 0, 0, 0, 0, 0, 0, 0, 0, 0, 0,
            0, 0, 0, 0, 0, 0, 0, 0, 0, 0, 0, 0, 0, 0, 0, 0, 0, 0, 0, 0, 0, 0, 0, 0, 0, 0, 0, 0, 0, 0,
            0, 0, 0, 0, 0, 0, 0, 0, 0, 0, 0, 0, 0, 0, 0, 0, 0, 0, 0, 0, 0, 0, 0, 0, 0, 0, 0, 0, 0, 0,
            0, 0, 0, 0, 0, 0, 0, 0, 0, 0, 620, 621, 0, 0, 0, 0, 0, 0, 619, 620, 621, 0, 0, 0, 0, 0, 0, 0, 0, 0,
            0, 0, 0, 0, 0, 0, 0, 0, 0, 0, 626, 627, 0, 0, 0, 0, 0, 0, 625, 626, 0, 0, 0, 0, 0, 0, 0, 0, 0, 0,
            0, 0, 0, 0, 0, 0, 0, 0, 0, 0, 632, 633, 0, 0, 0, 0, 0, 0, 631, 632, 0, 0, 0, 0, 0, 0, 0, 0, 0, 0,
            0, 0, 0, 0, 0, 0, 0, 0, 0, 0, 0, 0, 0, 0, 0, 0, 0, 0, 0, 0, 0, 0, 0, 0, 0, 0, 0, 0, 0, 0,
            0, 0, 0, 0, 0, 0, 0, 0, 0, 457, 458, 459, 460, 0, 0, 0, 0, 0, 0, 0, 0, 0, 0, 0, 0, 0, 0, 0, 0, 0,
            0, 0, 0, 0, 0, 0, 0, 0, 0, 476, 477, 478, 479, 0, 0, 0, 0, 0, 0, 0, 0, 0, 0, 0, 0, 0, 0, 0, 0, 0,
            0, 0, 0, 0, 0, 0, 0, 0, 0, 495, 496, 497, 498, 0, 0, 0, 0, 0, 0, 0, 0, 0, 0, 0, 0, 0, 0, 0, 0, 0,
            0, 0, 0, 0, 0, 0, 0, 0, 0, 514, 515, 516, 517, 0, 0, 0, 0, 0, 0, 0, 0, 0, 0, 0, 0, 0, 0, 0, 0, 0,
            0, 0, 0, 0, 0, 0, 0, 0, 0, 533, 534, 535, 536, 0, 0, 0, 0, 0, 0, 0, 0, 0, 0, 0, 0, 0, 0, 0, 0, 0,
            0, 0, 0, 0, 0, 0, 0, 0, 0, 552, 553, 554, 555, 0, 0, 0, 0, 0, 0, 0, 0, 0, 0, 0, 0, 0, 0, 0, 0, 0,
            0, 0, 0, 0, 0, 0, 0, 0, 0, 0, 0, 0, 0, 0, 0, 0, 0, 0, 0, 0, 0, 0, 0, 0, 0, 0, 0, 0, 0, 0,
            0, 0, 0, 0, 0, 0, 0, 0, 0, 0, 0, 0, 0, 0, 0, 0, 0, 0, 0, 0, 0, 0, 0, 0, 0, 0, 0, 0, 0, 0,
            0, 0, 0, 0, 0, 0, 0, 0, 0, 0, 0, 0, 0, 0, 0, 0, 0, 0, 0, 0, 0, 0, 0, 0, 0, 0, 0, 0, 0, 0,
            0, 0, 0, 0, 0, 0, 0, 0, 0, 0, 0, 0, 0, 0, 0, 0, 0, 0, 0, 0, 0, 0, 0, 0, 0, 0, 0, 0, 0, 0,
            0, 0, 0, 0, 0, 0, 0, 0, 0, 0, 0, 0, 0, 0, 0, 0, 0, 0, 0, 0, 0, 0, 0, 0, 0, 0, 0, 0, 0, 0,
            0, 0, 0, 0, 0, 0, 0, 0, 0, 162, 163, 164, 165, 0, 0, 0, 0, 0, 0, 0, 0, 0, 0, 0, 0, 0, 0, 0, 0, 0,
            0, 0, 0, 0, 0, 0, 0, 0, 0, 182, 183, 184, 185, 0, 0, 0, 0, 0, 0, 0, 0, 0, 0, 0, 0, 0, 0, 0, 0, 0,
            0, 0, 0, 0, 0, 0, 0, 0, 0, 202, 203, 204, 205, 0, 0, 0, 0, 0, 0, 0, 0, 0, 0, 0, 0, 0, 0, 0, 0, 0,
            0, 0, 0, 0, 0, 0, 0, 0, 0, 222, 223, 224, 225, 0, 0, 0, 0, 0, 0, 0, 0, 0, 0, 0, 0, 0, 0, 0, 0, 0,
            0, 0, 0, 0, 0, 0, 0, 0, 0, 242, 243, 244, 245, 0, 0, 0, 0, 0, 0, 0, 0, 0, 0, 0, 0, 0, 0, 0, 0, 0,
            0, 0, 0, 0, 0, 0, 0, 0, 0, 620, 621, 264, 265, 0, 0, 0, 0, 0, 0, 619, 620, 0, 0, 0, 0, 0, 0, 0, 0, 0,
            0, 0, 0, 0, 0, 0, 0, 0, 0, 626, 627, 0, 0, 0, 0, 0, 0, 0, 0, 625, 626, 0, 0, 0, 0, 0, 0, 0, 0, 0,
            0, 0, 0, 0, 0, 0, 0, 0, 0, 632, 633, 0, 0, 0, 0, 0, 0, 0, 0, 631, 632, 0, 0, 0, 0, 0, 0, 0, 0, 0,
            0, 0, 0, 0, 0, 0, 0, 0, 0, 0, 0, 0, 0, 0, 0, 0, 0, 0, 0, 0, 0, 0, 0, 0, 0, 0, 0, 0, 0, 0,
            0, 0, 0, 0, 0, 0, 0, 0, 0, 0, 0, 0, 0, 0, 0, 0, 0, 0, 0, 0, 0, 0, 0, 0, 0, 0, 0, 0, 0, 0,
            0, 0, 0, 0, 0, 0, 0, 0, 0, 0, 0, 0, 0, 0, 0, 0, 0, 0, 0, 0, 0, 0, 0, 0, 0, 0, 0, 0, 0, 0,
            0, 0, 0, 0, 0, 0, 0, 0, 0, 0, 0, 0, 0, 0, 0, 0, 0, 0, 0, 0, 0, 0, 0, 0, 0, 0, 0, 0, 0, 0,
            0, 0, 0, 0, 0, 0, 0, 0, 0, 0, 0, 0, 0, 0, 0, 0, 0, 0, 0, 0, 0, 0, 0, 0, 0, 0, 0, 0, 0, 0,
            0, 0, 0, 0, 0, 0, 0, 0, 0, 0, 0, 0, 0, 0, 0, 0, 0, 0, 0, 0, 0, 0, 0, 0, 0, 0, 0, 0, 0, 0,
            0, 0, 0, 0, 0, 0, 0, 0, 0, 0, 0, 0, 0, 0, 0, 0, 0, 0, 0, 0, 0, 0, 0, 0, 0, 0, 0, 0, 0, 0,
            0, 0, 0, 0, 0, 0, 0, 0, 0, 0, 0, 0, 0, 0, 0, 0, 0, 0, 0, 0, 0, 0, 0, 0, 0, 0, 0, 0, 0, 0,
            0, 0, 0, 0, 0, 0, 0, 0, 0, 0, 0, 0, 0, 0, 0, 0, 0, 458, 459, 460, 0, 0, 0, 0, 0, 0, 0, 0, 0, 0,
            0, 0, 0, 0, 0, 0, 0, 0, 0, 0, 0, 0, 0, 0, 0, 0, 0, 477, 478, 479, 0, 0, 0, 0, 0, 0, 0, 0, 0, 0,
            0, 0, 0, 0, 0, 0, 0, 0, 0, 0, 0, 0, 0, 0, 0, 0, 0, 496, 497, 498, 0, 0, 0, 0, 0, 0, 0, 0, 0, 0,
            0, 0, 0, 0, 0, 0, 0, 0, 0, 0, 0, 0, 0, 0, 0, 0, 0, 515, 516, 517, 0, 0, 0, 0, 0, 0, 0, 0, 0, 0,
            0, 0, 0, 0, 0, 0, 0, 0, 0, 0, 0, 0, 0, 0, 0, 0, 0, 534, 535, 536, 0, 0, 0, 0, 0, 0, 0, 0, 0, 0,
            0, 0, 0, 0, 0, 0, 0, 0, 0, 0, 0, 0, 0, 0, 0, 0, 0, 0, 0, 0, 0, 0, 0, 0, 0, 0, 0, 0, 0, 0,
            0, 0, 0, 0, 0, 0, 0, 0, 0, 0, 0, 0, 0, 0, 0, 0, 0, 0, 0, 0, 0, 0, 0, 0, 0, 0, 0, 0, 0, 0],
         "height":50,
         "id":4,
         "name":"DecorUpper1",
         "opacity":1,
         "type":"tilelayer",
         "visible":true,
         "width":30,
         "x":0,
         "y":0
        },
        {
         "draworder":"topdown",
         "id":7,
         "name":"BaseSpawn",
         "objects":[
                {
                 "height":0,
                 "id":1,
                 "name":"Base",
                 "point":true,
                 "properties":[
                        {
                         "name":"HP",
                         "type":"int",
                         "value":500
                        }],
                 "rotation":0,
                 "type":"",
                 "visible":true,
                 "width":0,
                 "x":480.515365930933,
                 "y":1216.07350300982
                }],
         "opacity":1,
         "type":"objectgroup",
         "visible":true,
         "x":0,
         "y":0
        },
        {
         "draworder":"topdown",
         "id":10,
         "name":"PlayerSpawn",
         "objects":[
                {
                 "height":0,
                 "id":7,
                 "name":"PlayerSpawn",
                 "point":true,
                 "rotation":0,
                 "type":"",
                 "visible":true,
                 "width":0,
                 "x":409.518539014942,
                 "y":1254.38111049622
                }],
         "opacity":1,
         "type":"objectgroup",
         "visible":true,
         "x":0,
         "y":0
        },
        {
         "draworder":"topdown",
         "id":9,
         "name":"PreSpawnedClusters",
         "objects":[
                {
                 "height":0,
                 "id":3,
                 "name":"Small",
                 "point":true,
                 "properties":[
                        {
                         "name":"enemyType",
                         "type":"string",
                         "value":"basic"
                        },
                        {
                         "name":"numSpawn",
                         "type":"int",
                         "value":5
                        }],
                 "rotation":0,
                 "type":"",
                 "visible":true,
                 "width":0,
                 "x":351.673883197803,
                 "y":675.889745485268
                },
                {
                 "height":0,
                 "id":4,
                 "name":"Small",
                 "point":true,
                 "properties":[
                        {
                         "name":"enemyType",
                         "type":"string",
                         "value":"basic"
                        },
                        {
                         "name":"numSpawn",
                         "type":"int",
                         "value":5
                        }],
                 "rotation":0,
                 "type":"",
                 "visible":true,
                 "width":0,
                 "x":608.828809800401,
                 "y":797.866722990812
                }],
         "opacity":1,
         "type":"objectgroup",
         "visible":true,
         "x":0,
         "y":0
        },
        {
         "draworder":"topdown",
         "id":8,
         "name":"SpawnerLocs",
         "objects":[
                {
                 "height":0,
                 "id":2,
                 "name":"Spawner",
                 "point":true,
                 "properties":[
                        {
                         "name":"HP",
                         "type":"int",
                         "value":100
                        },
                        {
                         "name":"InitDelay",
                         "type":"int",
                         "value":1
                        },
                        {
                         "name":"PrimaryEnemy",
                         "type":"string",
                         "value":"Basic"
                        },
                        {
                         "name":"RegDelay",
                         "type":"int",
                         "value":5
                        },
                        {
                         "name":"SecondaryEnemy",
                         "type":"string",
                         "value":"Basic"
                        },
                        {
                         "name":"TertiaryEnemy",
                         "type":"string",
                         "value":"Basic"
                        }],
                 "rotation":0,
                 "type":"",
                 "visible":true,
                 "width":0,
                 "x":480.515365930933,
                 "y":385.996409335727
                }],
         "opacity":1,
         "type":"objectgroup",
         "visible":true,
         "x":0,
         "y":0
        },
        {
         "draworder":"topdown",
         "id":11,
         "name":"DynamicDecor",
         "objects":[],
         "opacity":1,
         "type":"objectgroup",
         "visible":true,
         "x":0,
         "y":0
        }],
 "nextlayerid":13,
 "nextobjectid":8,
 "orientation":"orthogonal",
 "renderorder":"right-down",
 "tiledversion":"1.10.2",
 "tileheight":32,
 "tilesets":[
        {
         "firstgid":1,
         "source":"stiles.json"
        },
        {
         "firstgid":36,
         "source":"angelSkyscraper.json"
        },
        {
         "firstgid":113,
         "source":"devilMotel.json"
        },
        {
         "firstgid":333,
         "source":"devilSkyscraper.json"
        },
        {
         "firstgid":410,
         "source":"angelMotel.json"
        },
        {
         "firstgid":619,
         "source":"lamp.json"
        }],
 "tilewidth":32,
 "type":"map",
 "version":"1.10",
 "width":30
}
